odoo/addons/maintenance_equipment_tags/README.rst
odoo/addons/maintenance_equipment_tags/__init__.py
odoo/addons/maintenance_equipment_tags/__manifest__.py
odoo/addons/maintenance_equipment_tags/demo/maintenance_equipment_tags_demo.xml
odoo/addons/maintenance_equipment_tags/i18n/es.po
odoo/addons/maintenance_equipment_tags/i18n/it.po
odoo/addons/maintenance_equipment_tags/i18n/maintenance_equipment_tags.pot
odoo/addons/maintenance_equipment_tags/i18n/pt.po
odoo/addons/maintenance_equipment_tags/i18n/pt_BR.po
odoo/addons/maintenance_equipment_tags/models/__init__.py
odoo/addons/maintenance_equipment_tags/models/maintenance_equipment.py
odoo/addons/maintenance_equipment_tags/models/maintenance_equipment_tag.py
odoo/addons/maintenance_equipment_tags/readme/CONTRIBUTORS.md
odoo/addons/maintenance_equipment_tags/readme/DESCRIPTION.md
odoo/addons/maintenance_equipment_tags/security/ir.model.access.csv
odoo/addons/maintenance_equipment_tags/static/description/icon.png
odoo/addons/maintenance_equipment_tags/static/description/index.html
odoo/addons/maintenance_equipment_tags/views/maintenance_equipment.xml
odoo/addons/maintenance_equipment_tags/views/maintenance_equipment_tag.xml
odoo_addon_maintenance_equipment_tags-18.0.1.0.0.2.dist-info/METADATA
odoo_addon_maintenance_equipment_tags-18.0.1.0.0.2.dist-info/WHEEL
odoo_addon_maintenance_equipment_tags-18.0.1.0.0.2.dist-info/top_level.txt
odoo_addon_maintenance_equipment_tags-18.0.1.0.0.2.dist-info/RECORD
