Metadata-Version: 2.1
Name: odoo-addon-maintenance_equipment_tags
Version: 18.0.1.0.0.2
Requires-Python: >=3.10
Requires-Dist: odoo==18.0.*
Summary: Adds category tags to equipment
Home-page: https://github.com/OCA/maintenance
License: AGPL-3
Author: Creu Blanca,Odoo Community Association (OCA)
Author-email: support@odoo-community.org
Classifier: Programming Language :: Python
Classifier: Framework :: Odoo
Classifier: Framework :: Odoo :: 18.0
Classifier: License :: OSI Approved :: GNU Affero General Public License v3
